nestipy_jwt/__init__.py
nestipy_jwt/jwt_builder.py
nestipy_jwt/jwt_module.py
nestipy_jwt/jwt_service.py
nestipy_jwt-0.1.4.dist-info/LICENSE
nestipy_jwt-0.1.4.dist-info/METADATA
nestipy_jwt-0.1.4.dist-info/WHEEL
nestipy_jwt-0.1.4.dist-info/RECORD
