Metadata-Version: 2.1
Name: nestipy-jwt
Version: 0.1.4
Summary: 
Author: tsiresymila
Author-email: tsiresymila@gmail.com
Requires-Python: >=3.11,<4.0
Classifier: Programming Language :: Python :: 3
Classifier: Programming Language :: Python :: 3.11
Classifier: Programming Language :: Python :: 3.12
Requires-Dist: pyjwt (>=2.8.0,<3.0.0)
